task1/rom.sv
module rom #(
    parameter ADDRESS_WIDTH = 8,
    DATA_WIDTH = 8
    )(
        input logic clk,
        input logic [ADDRESS_WIDTH-1:0] addr,
        output logic [DATA_WIDTH-1:0] dout
    );

logic [DATA_WIDTH-1:0] rom_array [2**ADDRESS_WIDTH-1:0];

initial begin
    $display("Loading rom.");
    $readmemh("sinerom.mem", rom_array);
end;

always_ff @(posedge clk)

    dout <= rom_array [addr];

endmodule

task1/counter.sv
module counter #(
    parameter WIDTH = 8
)
(
    // interface signals
    input logic [WIDTH-1:0] incr,
    input logic clk, // clock
    input logic rst, // reset
    input logic en, // counter enable
    output logic [WIDTH-1:0] count // counter output
);

always_ff @ (posedge clk, posedge rst)
    if (rst) count <= {WIDTH{1'b0}};
    else if(en) count <= count + incr;
endmodule

task1/sinegen.sv
module sinegen #(parameter WIDTH = 8
)(
    input wire [WIDTH-1:0] incr,
    input wire clk,
    input wire en,
    input wire rst,
    output wire [WIDTH-1:0] dout
);
wire [WIDTH-1:0] addr;

counter counter (
    .clk (clk),
    .rst (rst),
    .en (en),
    .incr (incr),
    .count (addr)
);

rom sinerom (
    .clk (clk),
    .addr (addr),
    .dout (dout)
);
endmodule

task1/sinegen.vcd
$version Generated by VerilatedVcd $end
$date Thu Oct 27 20:15:53 2022 $end
$timescale 1ps $end

 $scope module TOP $end
  $var wire  1 $ clk $end
  $var wire  8 ' dout [7:0] $end
  $var wire  1 % en $end
  $var wire  8 # incr [7:0] $end
  $var wire  1 & rst $end
  $scope module sinegen $end
   $var wire 32 ) WIDTH [31:0] $end
   $var wire  8 ( addr [7:0] $end
   $var wire  1 $ clk $end
   $var wire  8 ' dout [7:0] $end
   $var wire  1 % en $end
   $var wire  8 # incr [7:0] $end
   $var wire  1 & rst $end
   $scope module counter $end
    $var wire 32 ) WIDTH [31:0] $end
    $var wire  1 $ clk $end
    $var wire  8 ( count [7:0] $end
    $var wire  1 % en $end
    $var wire  8 # incr [7:0] $end
    $var wire  1 & rst $end
   $upscope $end
   $scope module sinerom $end
    $var wire 32 ) ADDRESS_WIDTH [31:0] $end
    $var wire 32 ) DATA_WIDTH [31:0] $end
    $var wire  8 ( addr [7:0] $end
    $var wire  1 $ clk $end
    $var wire  8 ' dout [7:0] $end
   $upscope $end
  $upscope $end
 $upscope $end
$enddefinitions $end


#0
b00000001 #
0$
1%
0&
b00000000 '
b00000000 (
b00000000000000000000000000001000 )
#1
1$
#2
b00000000 #
0$
#3
1$
b11111110 '
#4
0$
#5
1$
#6
0$
#7
1$
#8
0$
#9
1$
#10
0$
#11
1$
#12
0$
#13
1$
#14
0$
#15
1$
#16
0$
#17
1$
#18
0$
#19
1$
#20
0$
#21
1$
#22
0$
#23
1$
#24
0$
#25
1$
#26
0$
#27
1$
#28
0$
#29
1$
#30
0$
#31
1$
#32
0$
#33
1$
#34
0$
#35
1$
#36
0$
#37
1$
#38
0$
#39
1$
#40
0$
#41
1$
#42
0$
#43
1$
#44
0$
#45
1$
#46
0$
#47
1$
#48
0$
#49
1$
#50
0$
#51
1$
#52
0$
#53
1$
#54
0$
#55
1$
#56
0$
#57
1$
#58
0$
#59
1$
#60
0$
#61
1$
#62
0$
#63
1$
#64
0$
#65
1$
#66
0$
#67
1$
#68
0$
#69
1$
#70
0$
#71
1$
#72
0$
#73
1$
#74
0$
#75
1$
#76
0$
#77
1$
#78
0$
#79
1$
#80
0$
#81
1$
#82
0$
#83
1$
#84
0$
#85
1$
#86
0$
#87
1$
#88
0$
#89
1$
#90
0$
#91
1$
#92
0$
#93
1$
#94
0$
#95
1$
#96
0$
#97
1$
#98
0$
#99
1$
#100
0$
#101
1$
#102
0$
#103
1$
#104
0$
#105
1$
#106
0$
#107
1$
#108
0$
#109
1$
#110
0$
#111
1$
#112
0$
#113
1$
#114
0$
#115
1$
#116
0$
#117
1$
#118
0$
#119
1$
#120
0$
#121
1$
#122
0$
#123
1$
#124
0$
#125
1$
#126
0$
#127
1$
#128
0$
#129
1$
#130
0$
#131
1$
#132
0$
#133
1$
#134
0$
#135
1$
#136
0$
#137
1$
#138
0$
#139
1$
#140
0$
#141
1$
#142
0$
#143
1$
#144
0$
#145
1$
#146
0$
#147
1$
#148
0$
#149
1$
#150
0$
#151
1$
#152
0$
#153
1$
#154
0$
#155
1$
#156
0$
#157
1$
#158
0$
#159
1$
#160
0$
#161
1$
#162
0$
#163
1$
#164
0$
#165
1$
#166
b00000001 #
0$
#167
1$
b00000001 (
#168
0$
#169
1$
b11111101 '
b00000010 (
#170
0$
#171
1$
b00000011 (
#172
0$
#173
1$
b00000100 (
#174
0$
#175
1$
b00000101 (
#176
0$
#177
1$
b00000110 (
#178
0$
#179
1$
b11111100 '
b00000111 (
#180
b00000010 #
0$
#181
1$
b00001001 (
#182
0$
#183
1$
b11111010 '
b00001011 (
#184
0$
#185
1$
b11111001 '
b00001101 (
#186
0$
#187
1$
b11110111 '
b00001111 (
#188
0$
#189
1$
b11110101 '
b00010001 (
#190
0$
#191
1$
b11110011 '
b00010011 (
#192
0$
#193
1$
b11110000 '
b00010101 (
#194
0$
#195
1$
b11101101 '
b00010111 (
#196
b00000011 #
0$
#197
1$
b11101010 '
b00011010 (
#198
0$
#199
1$
b11100101 '
b00011101 (
#200
0$
#201
1$
b11011111 '
b00100000 (
#202
0$
#203
1$
b11011000 '
b00100011 (
#204
0$
#205
1$
b11010001 '
b00100110 (
#206
0$
#207
1$
b11001010 '
b00101001 (
#208
0$
#209
1$
b11000010 '
b00101100 (
#210
b00000100 #
0$
#211
1$
b10111010 '
b00110000 (
#212
0$
#213
1$
b10101111 '
b00110100 (
#214
0$
#215
1$
b10100011 '
b00111000 (
#216
0$
#217
1$
b10010111 '
b00111100 (
#218
0$
#219
1$
b10001011 '
b01000000 (
#220
b00000101 #
0$
#221
1$
b01111110 '
b01000101 (
#222
0$
#223
1$
b01101111 '
b01001010 (
#224
0$
#225
1$
b01100000 '
b01001111 (
#226
0$
#227
1$
b01010001 '
b01010100 (
#228
b00000110 #
0$
#229
1$
b01000011 '
b01011010 (
#230
0$
#231
1$
b00110011 '
b01100000 (
#232
b00000111 #
0$
#233
1$
b00100101 '
b01100111 (
#234
0$
#235
1$
b00010111 '
b01101110 (
#236
b00001000 #
0$
#237
1$
b00001100 '
b01110110 (
#238
0$
#239
1$
b00000011 '
b01111110 (
#240
b00001001 #
0$
#241
1$
b00000000 '
b10000111 (
#242
0$
#243
1$
b00000001 '
b10010000 (
#244
0$
#245
1$
b00001001 '
b10011001 (
#246
b00001010 #
0$
#247
1$
b00010111 '
b10100011 (
#248
0$
#249
1$
b00101100 '
b10101101 (
#250
0$
#251
1$
b01000101 '
b10110111 (
#252
0$
#253
1$
b01100011 '
b11000001 (
#254
0$
#255
1$
b10000010 '
b11001011 (
#256
0$
#257
1$
b10100000 '
b11010101 (
#258
0$
#259
1$
b10111101 '
b11011111 (
#260
0$
#261
1$
b11010110 '
b11101001 (
#262
b00001011 #
0$
#263
1$
b11101010 '
b11110100 (
#264
0$
#265
1$
b11111000 '
b11111111 (
#266
0$
#267
1$
b11111101 '
b00001010 (
#268
0$
#269
1$
b11111010 '
b00010101 (
#270
b00001100 #
0$
#271
1$
b11101101 '
b00100001 (
#272
0$
#273
1$
b11010110 '
b00101101 (
#274
b00001101 #
0$
#275
1$
b10111000 '
b00111010 (
#276
0$
#277
1$
b10010001 '
b01000111 (
#278
0$
#279
1$
b01101001 '
b01010100 (
#280
0$
#281
1$
b01000011 '
b01100001 (
#282
0$
#283
1$
b00100011 '
b01101110 (
#284
0$
#285
1$
b00001100 '
b01111011 (
#286
0$
#287
1$
b00000000 '
b10001000 (
#288
0$
#289
1$
b00000010 '
b10010101 (
#290
0$
#291
1$
b00010000 '
b10100010 (
#292
0$
#293
1$
b00101001 '
b10101111 (
#294
0$
#295
1$
b01001011 '
b10111100 (
#296
0$
#297
1$
b01110010 '
b11001001 (
#298
0$
#299
1$
b10011010 '
b11010110 (
#300
0$
#301
1$
b11000000 '
b11100011 (
#302
0$
#303
1$
b11011111 '
b11110000 (
#304
0$
#305
1$
b11110100 '
b11111101 (
#306
0$
#307
1$
b11111101 '
b00001010 (
#308
0$
#309
1$
b11111010 '
b00010111 (
#310
0$
#311
1$
b11101010 '
b00100100 (
#312
0$
#313
1$
b11001111 '
b00110001 (
#314
0$
#315
1$
b10101100 '
b00111110 (
#316
0$
#317
1$
b10000101 '
b01001011 (
#318
b00001100 #
0$
#319
1$
b01011101 '
b01010111 (
#320
b00001011 #
0$
#321
1$
b00111011 '
b01100010 (
#322
0$
#323
1$
b00100000 '
b01101101 (
#324
b00001010 #
0$
#325
1$
b00001101 '
b01110111 (
#326
0$
#327
1$
b00000011 '
b10000001 (
#328
0$
#329
1$
b00000000 '
b10001011 (
#330
0$
#331
1$
b00000100 '
b10010101 (
#332
b00001001 #
0$
#333
1$
b00010000 '
b10011110 (
#334
0$
#335
1$
b00100000 '
b10100111 (
#336
0$
#337
1$
b00110101 '
b10110000 (
#338
0$
#339
1$
b01001110 '
b10111001 (
#340
0$
#341
1$
b01101001 '
b11000010 (
#342
0$
#343
1$
b10000101 '
b11001011 (
#344
0$
#345
1$
b10100000 '
b11010100 (
#346
0$
#347
1$
b10111010 '
b11011101 (
#348
b00001000 #
0$
#349
1$
b11010001 '
b11100101 (
#350
0$
#351
1$
b11100011 '
b11101101 (
#352
0$
#353
1$
b11110000 '
b11110101 (
#354
0$
#355
1$
b11111001 '
b11111101 (
#356
0$
#357
1$
b11111101 '
b00000101 (
#358
b00000111 #
0$
#359
1$
b00001100 (
#360
0$
#361
1$
b11111000 '
b00010011 (
#362
0$
#363
1$
b11110000 '
b00011010 (
#364
0$
#365
1$
b11100101 '
b00100001 (
#366
0$
#367
1$
b11010110 '
b00101000 (
#368
b00000110 #
0$
#369
1$
b11000101 '
b00101110 (
#370
0$
#371
1$
b10110101 '
b00110100 (
#372
0$
#373
1$
b10100011 '
b00111010 (
#374
0$
#375
1$
b10010001 '
b01000000 (
#376
0$
#377
1$
b01111110 '
b01000110 (
#378
b00000101 #
0$
#379
1$
b01101100 '
b01001011 (
#380
0$
#381
1$
b01011101 '
b01010000 (
#382
0$
#383
1$
b01001110 '
b01010101 (
#384
0$
#385
1$
b01000000 '
b01011010 (
#386
0$
#387
1$
b00110011 '
b01011111 (
#388
0$
#389
1$
b00100111 '
b01100100 (
#390
0$
#391
1$
b00011100 '
b01101001 (
#392
0$
#393
1$
b00010011 '
b01101110 (
#394
0$
#395
1$
b00001100 '
b01110011 (
#396
0$
#397
1$
b00000110 '
b01111000 (
#398
0$
#399
1$
b00000010 '
b01111101 (
#400
b00000100 #
0$
#401
1$
b00000000 '
b10000001 (
#402
0$
#403
1$
b10000101 (
#404
0$
#405
1$
b10001001 (
#406
0$
#407
1$
b00000011 '
b10001101 (
#408
0$
#409
1$
b00000110 '
b10010001 (
#410
0$
#411
1$
b00001010 '
b10010101 (
#412
0$
#413
1$
b00010000 '
b10011001 (
#414
0$
#415
1$
b00010111 '
b10011101 (
#416
0$
#417
1$
b00011110 '
b10100001 (
#418
0$
#419
1$
b00100111 '
b10100101 (
#420
0$
#421
1$
b00110000 '
b10101001 (
#422
0$
#423
1$
b00111011 '
b10101101 (
#424
b00000011 #
0$
#425
1$
b01000101 '
b10110000 (
#426
0$
#427
1$
b01001110 '
b10110011 (
#428
0$
#429
1$
b01010111 '
b10110110 (
#430
0$
#431
1$
b01100000 '
b10111001 (
#432
0$
#433
1$
b01101001 '
b10111100 (
#434
0$
#435
1$
b01110010 '
b10111111 (
#436
0$
#437
1$
b01111011 '
b11000010 (
#438
0$
#439
1$
b10000101 '
b11000101 (
#440
0$
#441
1$
b10001110 '
b11001000 (
#442
0$
#443
1$
b10010111 '
b11001011 (
#444
0$
#445
1$
b10100000 '
b11001110 (
#446
0$
#447
1$
b10101001 '
b11010001 (
#448
0$
#449
1$
b10110010 '
b11010100 (
#450
0$
#451
1$
b10111010 '
b11010111 (
#452
0$
#453
1$
b11000010 '
b11011010 (
#454
0$
#455
1$
b11001010 '
b11011101 (
#456
0$
#457
1$
b11010001 '
b11100000 (
#458
0$
#459
1$
b11011000 '
b11100011 (
#460
0$
#461
1$
b11011111 '
b11100110 (
#462
0$
#463
1$
b11100101 '
b11101001 (
#464
0$
#465
1$
b11101010 '
b11101100 (
#466
0$
#467
1$
b11101111 '
b11101111 (
#468
0$
#469
1$
b11110011 '
b11110010 (
#470
0$
#471
1$
b11110110 '
b11110101 (
#472
b00000010 #
0$
#473
1$
b11111001 '
b11110111 (
#474
0$
#475
1$
b11111010 '
b11111001 (
#476
0$
#477
1$
b11111100 '
b11111011 (
#478
0$
#479
1$
b11111101 '
b11111101 (
#480
0$
#481
1$
b11111111 (
#482
0$
#483
1$
b00000001 (
#484
0$
#485
1$
b00000011 (
#486
0$
#487
1$
b00000101 (
#488
0$
#489
1$
b00000111 (
#490
0$
#491
1$
b11111100 '
b00001001 (
#492
0$
#493
1$
b11111010 '
b00001011 (
#494
0$
#495
1$
b11111001 '
b00001101 (
#496
0$
#497
1$
b11110111 '
b00001111 (
#498
0$
#499
1$
b11110101 '
b00010001 (
#500
0$
#501
1$
b11110011 '
b00010011 (
#502
0$
#503
1$
b11110000 '
b00010101 (
#504
0$
#505
1$
b11101101 '
b00010111 (
#506
0$
#507
1$
b11101010 '
b00011001 (
#508
0$
#509
1$
b11100110 '
b00011011 (
#510
0$
#511
1$
b11100011 '
b00011101 (
#512
0$
#513
1$
b11011111 '
b00011111 (
#514
0$
#515
1$
b11011010 '
b00100001 (
#516
0$
#517
1$
b11010110 '
b00100011 (
#518
0$
#519
1$
b11010001 '
b00100101 (
#520
0$
#521
1$
b11001101 '
b00100111 (
#522
0$
#523
1$
b11001000 '
b00101001 (
#524
b00000001 #
0$
#525
1$
b11000010 '
b00101010 (
#526
0$
#527
1$
b11000000 '
b00101011 (
#528
0$
#529
1$
b10111101 '
b00101100 (
#530
0$
#531
1$
b10111010 '
b00101101 (
#532
0$
#533
1$
b10111000 '
b00101110 (
#534
0$
#535
1$
b10110101 '
b00101111 (
#536
0$
#537
1$
b10110010 '
b00110000 (
#538
0$
#539
1$
b10101111 '
b00110001 (
#540
0$
#541
1$
b10101100 '
b00110010 (
#542
0$
#543
1$
b10101001 '
b00110011 (
#544
0$
#545
1$
b10100110 '
b00110100 (
#546
0$
#547
1$
b10100011 '
b00110101 (
#548
0$
#549
1$
b10100000 '
b00110110 (
#550
0$
#551
1$
b10011101 '
b00110111 (
#552
0$
#553
1$
b10011010 '
b00111000 (
#554
0$
#555
1$
b10010111 '
b00111001 (
#556
0$
#557
1$
b10010100 '
b00111010 (
#558
0$
#559
1$
b10010001 '
b00111011 (
#560
0$
#561
1$
b10001110 '
b00111100 (
#562
0$
#563
1$
b10001011 '
b00111101 (
#564
0$
#565
1$
b10001000 '
b00111110 (
#566
0$
#567
1$
b10000101 '
b00111111 (
#568
0$
#569
1$
b10000010 '
b01000000 (
#570
0$
#571
1$
b01111110 '
b01000001 (
#572
0$
#573
1$
b01111011 '
b01000010 (
#574
0$
#575
1$
b01111000 '
b01000011 (
#576
0$
#577
1$
b01110101 '
b01000100 (
#578
0$
#579
1$
b01110010 '
b01000101 (
#580
0$
#581
1$
b01101111 '
b01000110 (
#582
0$
#583
1$
b01101100 '
b01000111 (
#584
0$
#585
1$
b01101001 '
b01001000 (
#586
0$
#587
1$
b01100110 '
b01001001 (
#588
0$
#589
1$
b01100011 '
b01001010 (
#590
0$
#591
1$
b01100000 '
b01001011 (
#592
0$
#593
1$
b01011101 '
b01001100 (
#594
0$
#595
1$
b01011010 '
b01001101 (
#596
0$
#597
1$
b01010111 '
b01001110 (
#598
0$
#599
1$
b01010100 '
b01001111 (
#600
0$
#601
1$
b01010001 '
b01010000 (
#602
0$
#603
1$
b01001110 '
b01010001 (
#604
0$
#605
1$
b01001011 '
b01010010 (
#606
0$
#607
1$
b01001000 '
b01010011 (
#608
0$
#609
1$
b01000101 '
b01010100 (
#610
0$
#611
1$
b01000011 '
b01010101 (
#612
0$
#613
1$
b01000000 '
b01010110 (
#614
0$
#615
1$
b00111101 '
b01010111 (
#616
0$
#617
1$
b00111011 '
b01011000 (
#618
0$
#619
1$
b00111000 '
b01011001 (
#620
0$
#621
1$
b00110101 '
b01011010 (
#622
0$
#623
1$
b00110011 '
b01011011 (
#624
0$
#625
1$
b00110000 '
b01011100 (
#626
0$
#627
1$
b00101110 '
b01011101 (
#628
0$
#629
1$
b00101100 '
b01011110 (
#630
0$
#631
1$
b00101001 '
b01011111 (
#632
0$
#633
1$
b00100111 '
b01100000 (
#634
0$
#635
1$
b00100101 '
b01100001 (
#636
0$
#637
1$
b00100011 '
b01100010 (
#638
0$
#639
1$
b00100000 '
b01100011 (
#640
0$
#641
1$
b00011110 '
b01100100 (
#642
0$
#643
1$
b00011100 '
b01100101 (
#644
0$
#645
1$
b00011010 '
b01100110 (
#646
0$
#647
1$
b00011000 '
b01100111 (
#648
0$
#649
1$
b00010111 '
b01101000 (
#650
0$
#651
1$
b00010101 '
b01101001 (
#652
0$
#653
1$
b00010011 '
b01101010 (
#654
0$
#655
1$
b00010010 '
b01101011 (
#656
0$
#657
1$
b00010000 '
b01101100 (
#658
0$
#659
1$
b00001110 '
b01101101 (
#660
0$
#661
1$
b00001101 '
b01101110 (
#662
0$
#663
1$
b00001100 '
b01101111 (
#664
0$
#665
1$
b00001010 '
b01110000 (
#666
0$
#667
1$
b00001001 '
b01110001 (
#668
0$
#669
1$
b00001000 '
b01110010 (
#670
0$
#671
1$
b00000111 '
b01110011 (
#672
0$
#673
1$
b00000110 '
b01110100 (
#674
0$
#675
1$
b00000101 '
b01110101 (
#676
0$
#677
1$
b00000100 '
b01110110 (
#678
0$
#679
1$
b00000011 '
b01110111 (
#680
0$
#681
1$
b01111000 (
#682
0$
#683
1$
b00000010 '
b01111001 (
#684
0$
#685
1$
b00000001 '
b01111010 (
#686
0$
#687
1$
b01111011 (
#688
0$
#689
1$
b00000000 '
b01111100 (
#690
0$
#691
1$
b01111101 (
#692
0$
#693
1$
b01111110 (
#694
0$
#695
1$
b01111111 (
#696
0$
#697
1$
b10000000 (
#698
0$
#699
1$
b10000001 (
#700
0$
#701
1$
b10000010 (
#702
0$
#703
1$
b10000011 (
#704
0$
#705
1$
b10000100 (
#706
b00000010 #
0$
#707
1$
b10000110 (
#708
0$
#709
1$
b00000001 '
b10001000 (
#710
0$
#711
1$
b00000010 '
b10001010 (
#712
0$
#713
1$
b00000011 '
b10001100 (
#714
0$
#715
1$
b00000101 '
b10001110 (
#716
0$
#717
1$
b00000111 '
b10010000 (
#718
b00000011 #
0$
#719
1$
b00001001 '
b10010011 (
#720
0$
#721
1$
b00001101 '
b10010110 (
#722
b00000100 #
0$
#723
1$
b00010010 '
b10011010 (
#724
0$
#725
1$
b00011000 '
b10011110 (
#726
b00000101 #
0$
#727
1$
b00100000 '
b10100011 (
#728
0$
#729
1$
b00101100 '
b10101000 (
#730
0$
#731
1$
b00111000 '
b10101101 (
#732
0$
#733
1$
b01000101 '
b10110010 (
#734
b00000110 #
0$
#735
1$
b01010100 '
b10111000 (
#736
0$
#737
1$
b01100110 '
b10111110 (
#738
0$
#739
1$
b01111000 '
b11000100 (
#740
b00000111 #
0$
#741
1$
b10001011 '
b11001011 (
#742
0$
#743
1$
b10100000 '
b11010010 (
#744
0$
#745
1$
b10110101 '
b11011001 (
#746
0$
#747
1$
b11001000 '
b11100000 (
#748
0$
#749
1$
b11011000 '
b11100111 (
#750
0$
#751
1$
b11100110 '
b11101110 (
#752
0$
#753
1$
b11110001 '
b11110101 (
#754
b00001000 #
0$
#755
1$
b11111001 '
b11111101 (
#756
0$
#757
1$
b11111101 '
b00000101 (
#758
0$
#759
1$
b00001101 (
#760
0$
#761
1$
b11110111 '
b00010101 (
#762
b00001001 #
0$
#763
1$
b11101101 '
b00011110 (
#764
0$
#765
1$
b11011101 '
b00100111 (
#766
0$
#767
1$
b11001000 '
b00110000 (
#768
0$
#769
1$
b10101111 '
b00111001 (
#770
b00001010 #
0$
#771
1$
b10010100 '
b01000011 (
#772
0$
#773
1$
b01110101 '
b01001101 (
#774
b00001011 #
0$
#775
1$
b01010111 '
b01011000 (
#776
0$
#777
1$
b00111000 '
b01100011 (
#778
b00001100 #
0$
#779
1$
b00011110 '
b01101111 (
#780
0$
#781
1$
b00001010 '
b01111011 (
#782
b00001101 #
0$
#783
1$
b00000000 '
b10001000 (
#784
b00001110 #
0$
#785
1$
b00000010 '
b10010110 (
#786
b00001111 #
0$
#787
1$
b00010010 '
b10100101 (
#788
b00010000 #
0$
#789
1$
b00110000 '
b10110101 (
#790
0$
#791
1$
b01011101 '
b11000101 (
#792
b00010001 #
0$
#793
1$
b10001110 '
b11010110 (
#794
b00010010 #
0$
#795
1$
b11000000 '
b11101000 (
#796
b00010011 #
0$
#797
1$
b11101000 '
b11111011 (
#798
b00010100 #
0$
#799
1$
b11111101 '
b00001111 (
#800
0$
#801
1$
b11110101 '
b00100011 (
#802
0$
#803
1$
b11010001 '
b00110111 (
#804
b00010101 #
0$
#805
1$
b10011010 '
b01001100 (
#806
0$
#807
1$
b01011010 '
b01100001 (
#808
0$
#809
1$
b00100011 '
b01110110 (
#810
b00010110 #
0$
#811
1$
b00000011 '
b10001100 (
#812
0$
#813
1$
b00000101 '
b10100010 (
#814
0$
#815
1$
b00101001 '
b10111000 (
#816
0$
#817
1$
b01100110 '
b11001110 (
#818
0$
#819
1$
b10101001 '
b11100100 (
#820
0$
#821
1$
b11100001 '
b11111010 (
#822
0$
#823
1$
b11111100 '
b00010000 (
#824
0$
#825
1$
b11110100 '
b00100110 (
#826
0$
#827
1$
b11001010 '
b00111100 (
#828
0$
#829
1$
b10001011 '
b01010010 (
#830
0$
#831
1$
b01001000 '
b01101000 (
#832
0$
#833
1$
b00010101 '
b01111110 (
#834
0$
#835
1$
b00000000 '
b10010100 (
#836
0$
#837
1$
b00001110 '
b10101010 (
#838
0$
#839
1$
b00111101 '
b11000000 (
#840
0$
#841
1$
b01111111 '
b11010110 (
#842
0$
#843
1$
b11000000 '
b11101100 (
#844
0$
#845
1$
b11101111 '
b00000010 (
#846
0$
#847
1$
b11111101 '
b00011000 (
#848
0$
#849
1$
b11101000 '
b00101110 (
#850
0$
#851
1$
b10110101 '
b01000100 (
#852
0$
#853
1$
b01110010 '
b01011010 (
#854
0$
#855
1$
b00110011 '
b01110000 (
#856
0$
#857
1$
b00001001 '
b10000110 (
#858
0$
#859
1$
b00000001 '
b10011100 (
#860
0$
#861
1$
b00011100 '
b10110010 (
#862
0$
#863
1$
b01010100 '
b11001000 (
#864
0$
#865
1$
b10010111 '
b11011110 (
#866
0$
#867
1$
b11010100 '
b11110100 (
#868
0$
#869
1$
b11111000 '
b00001010 (
#870
0$
#871
1$
b11111010 '
b00100000 (
#872
0$
#873
1$
b11011000 '
b00110110 (
#874
0$
#875
1$
b10011101 '
b01001100 (
#876
0$
#877
1$
b01011010 '
b01100010 (
#878
0$
#879
1$
b00100000 '
b01111000 (
#880
0$
#881
1$
b00000010 '
b10001110 (
#882
0$
#883
1$
b00000111 '
b10100100 (
#884
0$
#885
1$
b00101110 '
b10111010 (
#886
0$
#887
1$
b01101100 '
b11010000 (
#888
0$
#889
1$
b10101111 '
b11100110 (
#890
0$
#891
1$
b11100101 '
b11111100 (
#892
0$
#893
1$
b11111101 '
b00010010 (
#894
0$
#895
1$
b11110001 '
b00101000 (
#896
0$
#897
1$
b11000101 '
b00111110 (
#898
0$
#899
1$
b10000101 '
b01010100 (
#900
0$
#901
1$
b01000011 '
b01101010 (
#902
0$
#903
1$
b00010010 '
b10000000 (
#904
0$
#905
1$
b00000000 '
b10010110 (
#906
0$
#907
1$
b00010010 '
b10101100 (
#908
0$
#909
1$
b01000011 '
b11000010 (
#910
0$
#911
1$
b10000101 '
b11011000 (
#912
0$
#913
1$
b11000101 '
b11101110 (
#914
0$
#915
1$
b11110001 '
b00000100 (
#916
0$
#917
1$
b11111101 '
b00011010 (
#918
0$
#919
1$
b11100101 '
b00110000 (
#920
0$
#921
1$
b10101111 '
b01000110 (
#922
0$
#923
1$
b01101100 '
b01011100 (
#924
0$
#925
1$
b00101110 '
b01110010 (
#926
0$
#927
1$
b00000111 '
b10001000 (
#928
0$
#929
1$
b00000010 '
b10011110 (
#930
b00010101 #
0$
#931
1$
b00100000 '
b10110011 (
#932
0$
#933
1$
b01010111 '
b11001000 (
#934
0$
#935
1$
b10010111 '
b11011101 (
#936
0$
#937
1$
b11010001 '
b11110010 (
#938
b00010100 #
0$
#939
1$
b11110110 '
b00000110 (
#940
0$
#941
1$
b11111100 '
b00011010 (
#942
0$
#943
1$
b11100101 '
b00101110 (
#944
0$
#945
1$
b10110101 '
b01000010 (
#946
0$
#947
1$
b01111000 '
b01010110 (
#948
0$
#949
1$
b00111101 '
b01101010 (
#950
0$
#951
1$
b00010010 '
b01111110 (
#952
0$
#953
1$
b00000000 '
b10010010 (
#954
0$
#955
1$
b00001100 '
b10100110 (
#956
0$
#957
1$
b00110011 '
b10111010 (
#958
0$
#959
1$
b01101100 '
b11001110 (
#960
0$
#961
1$
b10101001 '
b11100010 (
#962
0$
#963
1$
b11011101 '
b11110110 (
#964
0$
#965
1$
b11111010 '
b00001010 (
#966
0$
#967
1$
b00011110 (
#968
0$
#969
1$
b11011101 '
b00110010 (
#970
0$
#971
1$
b10101001 '
b01000110 (
#972
0$
#973
1$
b01101100 '
b01011010 (
#974
0$
#975
1$
b00110011 '
b01101110 (
#976
0$
#977
1$
b00001100 '
b10000010 (
#978
0$
#979
1$
b00000000 '
b10010110 (
#980
0$
#981
1$
b00010010 '
b10101010 (
#982
0$
#983
1$
b00111101 '
b10111110 (
#984
0$
#985
1$
b01111000 '
b11010010 (
#986
0$
#987
1$
b10110101 '
b11100110 (
#988
0$
#989
1$
b11100101 '
b11111010 (
#990
0$
#991
1$
b11111100 '
b00001110 (
#992
0$
#993
1$
b11110110 '
b00100010 (
#994
0$
#995
1$
b11010100 '
b00110110 (
#996
0$
#997
1$
b10011101 '
b01001010 (
#998
0$
#999
1$
b01100000 '
b01011110 (
#1000
0$
#1001
1$
b00101001 '
b01110010 (
#1002
0$
#1003
1$
b00000111 '
b10000110 (
#1004
0$
#1005
1$
b00000001 '
b10011010 (
#1006
0$
#1007
1$
b00011000 '
b10101110 (
#1008
0$
#1009
1$
b01001000 '
b11000010 (
#1010
0$
#1011
1$
b10000101 '
b11010110 (
#1012
0$
#1013
1$
b11000000 '
b11101010 (
#1014
0$
#1015
1$
b11101011 '
b11111110 (
#1016
0$
#1017
1$
b11111101 '
b00010010 (
#1018
0$
#1019
1$
b11110001 '
b00100110 (
#1020
0$
#1021
1$
b11001010 '
b00111010 (
#1022
0$
#1023
1$
b10010001 '
b01001110 (
#1024
0$
#1025
1$
b01010100 '
b01100010 (
#1026
0$
#1027
1$
b00100000 '
b01110110 (
#1028
0$
#1029
1$
b00000011 '
b10001010 (
#1030
0$
#1031
1$
b10011110 (
#1032
0$
#1033
1$
b00100000 '
b10110010 (
#1034
0$
#1035
1$
b01010100 '
b11000110 (
#1036
0$
#1037
1$
b10010001 '
b11011010 (
#1038
0$
#1039
1$
b11001010 '
b11101110 (
#1040
0$
#1041
1$
b11110001 '
b00000010 (
#1042
0$
#1043
1$
b11111101 '
b00010110 (
#1044
0$
#1045
1$
b11101011 '
b00101010 (
#1046
0$
#1047
1$
b11000000 '
b00111110 (
#1048
0$
#1049
1$
b10000101 '
b01010010 (
#1050
0$
#1051
1$
b01001000 '
b01100110 (
#1052
0$
#1053
1$
b00011000 '
b01111010 (
#1054
0$
#1055
1$
b00000001 '
b10001110 (
#1056
0$
#1057
1$
b00000111 '
b10100010 (
#1058
0$
#1059
1$
b00101001 '
b10110110 (
#1060
0$
#1061
1$
b01100000 '
b11001010 (
#1062
0$
#1063
1$
b10011101 '
b11011110 (
#1064
0$
#1065
1$
b11010100 '
b11110010 (
#1066
0$
#1067
1$
b11110110 '
b00000110 (
#1068
0$
#1069
1$
b11111100 '
b00011010 (
#1070
0$
#1071
1$
b11100101 '
b00101110 (
#1072
0$
#1073
1$
b10110101 '
b01000010 (
#1074
b00010011 #
0$
#1075
1$
b01111000 '
b01010101 (
#1076
0$
#1077
1$
b01000000 '
b01101000 (
#1078
0$
#1079
1$
b00010101 '
b01111011 (
#1080
0$
#1081
1$
b00000000 '
b10001110 (
#1082
0$
#1083
1$
b00000111 '
b10100001 (
#1084
0$
#1085
1$
b00100111 '
b10110100 (
#1086
0$
#1087
1$
b01011010 '
b11000111 (
#1088
0$
#1089
1$
b10010100 '
b11011010 (
#1090
0$
#1091
1$
b11001010 '
b11101101 (
#1092
0$
#1093
1$
b11110000 '
b00000000 (
#1094
0$
#1095
1$
b11111110 '
b00010011 (
#1096
0$
#1097
1$
b11110000 '
b00100110 (
#1098
0$
#1099
1$
b11001010 '
b00111001 (
#1100
0$
#1101
1$
b10010100 '
b01001100 (
#1102
0$
#1103
1$
b01011010 '
b01011111 (
#1104
0$
#1105
1$
b00100111 '
b01110010 (
#1106
0$
#1107
1$
b00000111 '
b10000101 (
#1108
0$
#1109
1$
b00000000 '
b10011000 (
#1110
0$
#1111
1$
b00010101 '
b10101011 (
#1112
0$
#1113
1$
b01000000 '
b10111110 (
#1114
0$
#1115
1$
b01111000 '
b11010001 (
#1116
0$
#1117
1$
b10110010 '
b11100100 (
#1118
0$
#1119
1$
b11100001 '
b11110111 (
#1120
0$
#1121
1$
b11111010 '
b00001010 (
#1122
0$
#1123
1$
b00011101 (
#1124
0$
#1125
1$
b11011111 '
b00110000 (
#1126
b00010010 #
0$
