task2/rom.sv
module rom #(
    parameter ADDRESS_WIDTH = 8,
    DATA_WIDTH = 8
    )(
        input logic clk,
        input logic [ADDRESS_WIDTH-1:0] addr1,
        input logic [ADDRESS_WIDTH-1:0] addr2,
        output logic [DATA_WIDTH-1:0] dout1,
        output logic [DATA_WIDTH-1:0] dout2
    );

logic [DATA_WIDTH-1:0] rom_array [2**ADDRESS_WIDTH-1:0];

initial begin
    $display("Loading rom.");
    $readmemh("sinerom.mem", rom_array);
end;

always_ff @(posedge clk)begin

    dout1 <= rom_array [addr1];
    dout2 <= rom_array [addr2];
end

endmodule

task2/offset.sv
module offset #(
    WIDTH = 8
) (
    input [WIDTH-1:0] counter_input,
    input [WIDTH-1:0] offset,
    output [WIDTH-1:0] offset_address
);

assign offset_address = counter_input + offset;
    
endmodule

task3/counter.sv
module counter #(
    parameter WIDTH = 9
)
(
    // interface signals
    input logic clk, // clock
    input logic rst, // reset
    input logic en, // counter enable
    output logic [WIDTH-1:0] count // counter output
);

always_ff @ (posedge clk, posedge rst)
    if (rst) count <= {WIDTH{1'b0}};
    else count <= count + {{WIDTH-1{1'b0}}, en};
endmodule

task2/sinegen.sv
module sinegen #(parameter WIDTH = 8
)(
    input wire [WIDTH-1:0] incr,
    input wire clk,
    input wire en,
    input wire rst,
    output wire [WIDTH-1:0] data1,
    output wire [WIDTH-1:0] data2
);
wire [WIDTH-1:0] addr1;
wire [WIDTH-1:0] addr2;

counter counter (
    .clk (clk),
    .rst (rst),
    .en (en),
    .count (addr1)
);

offset offset1 (
    .counter_input(addr1),
    .offset (incr),
    .offset_address (addr2)
);

rom sinerom (
    .clk (clk),
    .addr1 (addr1),
    .addr2 (addr2),
    .dout1 (data1),
    .dout2 (data2)
);

endmodule

task2/sinegen.vcd
$version Generated by VerilatedVcd $end
$date Fri Oct 28 14:29:57 2022 $end
$timescale 1ps $end

 $scope module TOP $end
  $var wire  1 $ clk $end
  $var wire  8 ' data1 [7:0] $end
  $var wire  8 ( data2 [7:0] $end
  $var wire  1 % en $end
  $var wire  8 # incr [7:0] $end
  $var wire  1 & rst $end
  $scope module sinegen $end
   $var wire 32 + WIDTH [31:0] $end
   $var wire  8 ) addr1 [7:0] $end
   $var wire  8 * addr2 [7:0] $end
   $var wire  1 $ clk $end
   $var wire  8 ' data1 [7:0] $end
   $var wire  8 ( data2 [7:0] $end
   $var wire  1 % en $end
   $var wire  8 # incr [7:0] $end
   $var wire  1 & rst $end
   $scope module counter $end
    $var wire 32 + WIDTH [31:0] $end
    $var wire  1 $ clk $end
    $var wire  8 ) count [7:0] $end
    $var wire  1 % en $end
    $var wire  1 & rst $end
   $upscope $end
   $scope module offset1 $end
    $var wire 32 + WIDTH [31:0] $end
    $var wire  8 ) counter_input [7:0] $end
    $var wire  8 # offset [7:0] $end
    $var wire  8 * offset_address [7:0] $end
   $upscope $end
   $scope module sinerom $end
    $var wire 32 + ADDRESS_WIDTH [31:0] $end
    $var wire 32 + DATA_WIDTH [31:0] $end
    $var wire  8 ) addr1 [7:0] $end
    $var wire  8 * addr2 [7:0] $end
    $var wire  1 $ clk $end
    $var wire  8 ' dout1 [7:0] $end
    $var wire  8 ( dout2 [7:0] $end
   $upscope $end
  $upscope $end
 $upscope $end
$enddefinitions $end


#0
b00000000 #
0$
1%
0&
b00000000 '
b00000000 (
b00000000 )
b00000000 *
b00000000000000000000000000001000 +
#1
1$
#2
b00110011 #
0$
b00110011 *
#3
1$
b11111110 '
b10100110 (
b00000001 )
b00110100 *
#4
0$
#5
1$
b11111101 '
b10100011 (
b00000010 )
b00110101 *
#6
0$
#7
1$
b10100000 (
b00000011 )
b00110110 *
#8
0$
#9
1$
b10011101 (
b00000100 )
b00110111 *
#10
0$
#11
1$
b10011010 (
b00000101 )
b00111000 *
#12
0$
#13
1$
b10010111 (
b00000110 )
b00111001 *
#14
0$
#15
1$
b11111100 '
b10010100 (
b00000111 )
b00111010 *
#16
0$
#17
1$
b10010001 (
b00001000 )
b00111011 *
#18
0$
#19
1$
b11111011 '
b10001110 (
b00001001 )
b00111100 *
#20
0$
#21
1$
b11111010 '
b10001011 (
b00001010 )
b00111101 *
#22
0$
#23
1$
b10001000 (
b00001011 )
b00111110 *
#24
0$
#25
1$
b11111001 '
b10000101 (
b00001100 )
b00111111 *
#26
0$
#27
1$
b11111000 '
b10000010 (
b00001101 )
b01000000 *
#28
0$
#29
1$
b11110111 '
b01111110 (
b00001110 )
b01000001 *
#30
0$
#31
1$
b11110110 '
b01111011 (
b00001111 )
b01000010 *
#32
0$
#33
1$
b11110101 '
b01111000 (
b00010000 )
b01000011 *
#34
0$
#35
1$
b11110100 '
b01110101 (
b00010001 )
b01000100 *
#36
0$
#37
1$
b11110011 '
b01110010 (
b00010010 )
b01000101 *
#38
0$
#39
1$
b11110001 '
b01101111 (
b00010011 )
b01000110 *
#40
0$
#41
1$
b11110000 '
b01101100 (
b00010100 )
b01000111 *
#42
0$
#43
1$
b11101111 '
b01101001 (
b00010101 )
b01001000 *
#44
0$
#45
1$
b11101101 '
b01100110 (
b00010110 )
b01001001 *
#46
0$
#47
1$
b11101011 '
b01100011 (
b00010111 )
b01001010 *
#48
0$
#49
1$
b11101010 '
b01100000 (
b00011000 )
b01001011 *
#50
0$
#51
1$
b11101000 '
b01011101 (
b00011001 )
b01001100 *
#52
0$
#53
1$
b11100110 '
b01011010 (
b00011010 )
b01001101 *
#54
0$
#55
1$
b11100101 '
b01010111 (
b00011011 )
b01001110 *
#56
0$
#57
1$
b11100011 '
b01010100 (
b00011100 )
b01001111 *
#58
0$
#59
1$
b11100001 '
b01010001 (
b00011101 )
b01010000 *
#60
0$
#61
1$
b11011111 '
b01001110 (
b00011110 )
b01010001 *
#62
0$
#63
1$
b11011101 '
b01001011 (
b00011111 )
b01010010 *
#64
0$
#65
1$
b11011010 '
b01001000 (
b00100000 )
b01010011 *
#66
0$
#67
1$
b11011000 '
b01000101 (
b00100001 )
b01010100 *
#68
0$
#69
1$
b11010110 '
b01000011 (
b00100010 )
b01010101 *
#70
0$
#71
1$
b11010100 '
b01000000 (
b00100011 )
b01010110 *
#72
0$
#73
1$
b11010001 '
b00111101 (
b00100100 )
b01010111 *
#74
0$
#75
1$
b11001111 '
b00111011 (
b00100101 )
b01011000 *
#76
0$
#77
1$
b11001101 '
b00111000 (
b00100110 )
b01011001 *
#78
0$
#79
1$
b11001010 '
b00110101 (
b00100111 )
b01011010 *
#80
0$
#81
1$
b11001000 '
b00110011 (
b00101000 )
b01011011 *
#82
0$
#83
1$
b11000101 '
b00110000 (
b00101001 )
b01011100 *
#84
0$
#85
1$
b11000010 '
b00101110 (
b00101010 )
b01011101 *
#86
0$
#87
1$
b11000000 '
b00101100 (
b00101011 )
b01011110 *
#88
0$
#89
1$
b10111101 '
b00101001 (
b00101100 )
b01011111 *
#90
0$
#91
1$
b10111010 '
b00100111 (
b00101101 )
b01100000 *
#92
0$
#93
1$
b10111000 '
b00100101 (
b00101110 )
b01100001 *
#94
0$
#95
1$
b10110101 '
b00100011 (
b00101111 )
b01100010 *
#96
0$
#97
1$
b10110010 '
b00100000 (
b00110000 )
b01100011 *
#98
0$
#99
1$
b10101111 '
b00011110 (
b00110001 )
b01100100 *
#100
0$
#101
1$
b10101100 '
b00011100 (
b00110010 )
b01100101 *
#102
0$
#103
1$
b10101001 '
b00011010 (
b00110011 )
b01100110 *
#104
0$
#105
1$
b10100110 '
b00011000 (
b00110100 )
b01100111 *
#106
0$
#107
1$
b10100011 '
b00010111 (
b00110101 )
b01101000 *
#108
0$
#109
1$
b10100000 '
b00010101 (
b00110110 )
b01101001 *
#110
0$
#111
1$
b10011101 '
b00010011 (
b00110111 )
b01101010 *
#112
0$
#113
1$
b10011010 '
b00010010 (
b00111000 )
b01101011 *
#114
0$
#115
1$
b10010111 '
b00010000 (
b00111001 )
b01101100 *
#116
0$
#117
1$
b10010100 '
b00001110 (
b00111010 )
b01101101 *
#118
0$
#119
1$
b10010001 '
b00001101 (
b00111011 )
b01101110 *
#120
0$
#121
1$
b10001110 '
b00001100 (
b00111100 )
b01101111 *
#122
0$
#123
1$
b10001011 '
b00001010 (
b00111101 )
b01110000 *
#124
0$
#125
1$
b10001000 '
b00001001 (
b00111110 )
b01110001 *
#126
0$
#127
1$
b10000101 '
b00001000 (
b00111111 )
b01110010 *
#128
0$
#129
1$
b10000010 '
b00000111 (
b01000000 )
b01110011 *
#130
0$
#131
1$
b01111110 '
b00000110 (
b01000001 )
b01110100 *
#132
0$
#133
1$
b01111011 '
b00000101 (
b01000010 )
b01110101 *
#134
0$
#135
1$
b01111000 '
b00000100 (
b01000011 )
b01110110 *
#136
0$
#137
1$
b01110101 '
b00000011 (
b01000100 )
b01110111 *
#138
0$
#139
1$
b01110010 '
b01000101 )
b01111000 *
#140
0$
#141
1$
b01101111 '
b00000010 (
b01000110 )
b01111001 *
#142
0$
#143
1$
b01101100 '
b00000001 (
b01000111 )
b01111010 *
#144
0$
#145
1$
b01101001 '
b01001000 )
b01111011 *
#146
0$
#147
1$
b01100110 '
b00000000 (
b01001001 )
b01111100 *
#148
0$
#149
1$
b01100011 '
b01001010 )
b01111101 *
#150
0$
#151
1$
b01100000 '
b01001011 )
b01111110 *
#152
0$
#153
1$
b01011101 '
b01001100 )
b01111111 *
#154
0$
#155
1$
b01011010 '
b01001101 )
b10000000 *
#156
0$
#157
1$
b01010111 '
b01001110 )
b10000001 *
#158
0$
#159
1$
b01010100 '
b01001111 )
b10000010 *
#160
0$
#161
1$
b01010001 '
b01010000 )
b10000011 *
#162
0$
#163
1$
b01001110 '
b01010001 )
b10000100 *
#164
0$
#165
1$
b01001011 '
b01010010 )
b10000101 *
#166
0$
#167
1$
b01001000 '
b01010011 )
b10000110 *
#168
0$
#169
1$
b01000101 '
b00000001 (
b01010100 )
b10000111 *
#170
0$
#171
1$
b01000011 '
b01010101 )
b10001000 *
#172
0$
#173
1$
b01000000 '
b00000010 (
b01010110 )
b10001001 *
#174
0$
#175
1$
b00111101 '
b00000011 (
b01010111 )
b10001010 *
#176
0$
#177
1$
b00111011 '
b01011000 )
b10001011 *
#178
0$
#179
1$
b00111000 '
b00000100 (
b01011001 )
b10001100 *
#180
0$
#181
1$
b00110101 '
b00000101 (
b01011010 )
b10001101 *
#182
0$
#183
1$
b00110011 '
b00000110 (
b01011011 )
b10001110 *
#184
0$
#185
1$
b00110000 '
b00000111 (
b01011100 )
b10001111 *
#186
0$
#187
1$
b00101110 '
b00001000 (
b01011101 )
b10010000 *
#188
0$
#189
1$
b00101100 '
b00001001 (
b01011110 )
b10010001 *
#190
0$
#191
1$
b00101001 '
b00001010 (
b01011111 )
b10010010 *
#192
0$
#193
1$
b00100111 '
b00001100 (
b01100000 )
b10010011 *
#194
0$
#195
1$
b00100101 '
b00001101 (
b01100001 )
b10010100 *
#196
0$
#197
1$
b00100011 '
b00001110 (
b01100010 )
b10010101 *
#198
0$
#199
1$
b00100000 '
b00010000 (
b01100011 )
b10010110 *
#200
0$
#201
1$
b00011110 '
b00010010 (
b01100100 )
b10010111 *
#202
0$
#203
1$
b00011100 '
b00010011 (
b01100101 )
b10011000 *
#204
0$
#205
1$
b00011010 '
b00010101 (
b01100110 )
b10011001 *
#206
0$
#207
1$
b00011000 '
b00010111 (
b01100111 )
b10011010 *
#208
0$
#209
1$
b00010111 '
b00011000 (
b01101000 )
b10011011 *
#210
0$
#211
1$
b00010101 '
b00011010 (
b01101001 )
b10011100 *
#212
0$
#213
1$
b00010011 '
b00011100 (
b01101010 )
b10011101 *
#214
0$
#215
1$
b00010010 '
b00011110 (
b01101011 )
b10011110 *
#216
0$
#217
1$
b00010000 '
b00100000 (
b01101100 )
b10011111 *
#218
b00110100 #
0$
b10100000 *
#219
1$
b00001110 '
b00100101 (
b01101101 )
b10100001 *
#220
0$
#221
1$
b00001101 '
b00100111 (
b01101110 )
b10100010 *
#222
0$
#223
1$
b00001100 '
b00101001 (
b01101111 )
b10100011 *
#224
0$
#225
1$
b00001010 '
b00101100 (
b01110000 )
b10100100 *
#226
0$
#227
1$
b00001001 '
b00101110 (
b01110001 )
b10100101 *
#228
0$
#229
1$
b00001000 '
b00110000 (
b01110010 )
b10100110 *
#230
0$
#231
1$
b00000111 '
b00110011 (
b01110011 )
b10100111 *
#232
b00110101 #
0$
b10101000 *
#233
1$
b00000110 '
b00111000 (
b01110100 )
b10101001 *
#234
0$
#235
1$
b00000101 '
b00111011 (
b01110101 )
b10101010 *
#236
0$
#237
1$
b00000100 '
b00111101 (
b01110110 )
b10101011 *
#238
0$
#239
1$
b00000011 '
b01000000 (
b01110111 )
b10101100 *
#240
0$
#241
1$
b01000011 (
b01111000 )
b10101101 *
#242
b00110110 #
0$
b10101110 *
#243
1$
b00000010 '
b01001000 (
b01111001 )
b10101111 *
#244
0$
#245
1$
b00000001 '
b01001011 (
b01111010 )
b10110000 *
#246
b00110111 #
0$
b10110001 *
#247
1$
b01010001 (
b01111011 )
b10110010 *
#248
0$
#249
1$
b00000000 '
b01010100 (
b01111100 )
b10110011 *
#250
0$
#251
1$
b01010111 (
b01111101 )
b10110100 *
#252
0$
#253
1$
b01011010 (
b01111110 )
b10110101 *
#254
0$
#255
1$
b01011101 (
b01111111 )
b10110110 *
#256
0$
#257
1$
b01100000 (
b10000000 )
b10110111 *
#258
b00111000 #
0$
b10111000 *
#259
1$
b01100110 (
b10000001 )
b10111001 *
#260
0$
#261
1$
b01101001 (
b10000010 )
b10111010 *
#262
0$
#263
1$
b01101100 (
b10000011 )
b10111011 *
#264
0$
#265
1$
b01101111 (
b10000100 )
b10111100 *
#266
0$
#267
1$
b01110010 (
b10000101 )
b10111101 *
#268
0$
#269
1$
b01110101 (
b10000110 )
b10111110 *
#270
0$
#271
1$
b00000001 '
b01111000 (
b10000111 )
b10111111 *
#272
0$
#273
1$
b01111011 (
b10001000 )
b11000000 *
#274
b00111001 #
0$
b11000001 *
#275
1$
b00000010 '
b10000010 (
b10001001 )
b11000010 *
#276
0$
#277
1$
b00000011 '
b10000101 (
b10001010 )
b11000011 *
#278
0$
#279
1$
b10001000 (
b10001011 )
b11000100 *
#280
0$
#281
1$
b00000100 '
b10001011 (
b10001100 )
b11000101 *
#282
0$
#283
1$
b00000101 '
b10001110 (
b10001101 )
b11000110 *
#284
0$
#285
1$
b00000110 '
b10010001 (
b10001110 )
b11000111 *
#286
b00111010 #
0$
b11001000 *
#287
1$
b00000111 '
b10010111 (
b10001111 )
b11001001 *
#288
0$
#289
1$
b00001000 '
b10011010 (
b10010000 )
b11001010 *
#290
0$
#291
1$
b00001001 '
b10011101 (
b10010001 )
b11001011 *
#292
0$
#293
1$
b00001010 '
b10100000 (
b10010010 )
b11001100 *
#294
b00111011 #
0$
b11001101 *
#295
1$
b00001100 '
b10100110 (
b10010011 )
b11001110 *
#296
0$
#297
1$
b00001101 '
b10101001 (
b10010100 )
b11001111 *
#298
0$
#299
1$
b00001110 '
b10101100 (
b10010101 )
b11010000 *
#300
0$
#301
1$
b00010000 '
b10101111 (
b10010110 )
b11010001 *
#302
0$
#303
1$
b00010010 '
b10110010 (
b10010111 )
b11010010 *
#304
0$
#305
1$
b00010011 '
b10110101 (
b10011000 )
b11010011 *
#306
0$
#307
1$
b00010101 '
b10111000 (
b10011001 )
b11010100 *
#308
0$
#309
1$
b00010111 '
b10111010 (
b10011010 )
b11010101 *
#310
b00111100 #
0$
b11010110 *
#311
1$
b00011000 '
b11000000 (
b10011011 )
b11010111 *
#312
0$
#313
1$
b00011010 '
b11000010 (
b10011100 )
b11011000 *
#314
0$
#315
1$
b00011100 '
b11000101 (
b10011101 )
b11011001 *
#316
0$
#317
1$
b00011110 '
b11001000 (
b10011110 )
b11011010 *
#318
0$
#319
1$
b00100000 '
b11001010 (
b10011111 )
b11011011 *
#320
0$
#321
1$
b00100011 '
b11001101 (
b10100000 )
b11011100 *
#322
0$
#323
1$
b00100101 '
b11001111 (
b10100001 )
b11011101 *
#324
0$
#325
1$
b00100111 '
b11010001 (
b10100010 )
b11011110 *
#326
0$
#327
1$
b00101001 '
b11010100 (
b10100011 )
b11011111 *
#328
0$
#329
1$
b00101100 '
b11010110 (
b10100100 )
b11100000 *
#330
0$
#331
1$
b00101110 '
b11011000 (
b10100101 )
b11100001 *
#332
0$
#333
1$
b00110000 '
b11011010 (
b10100110 )
b11100010 *
#334
0$
#335
1$
b00110011 '
b11011101 (
b10100111 )
b11100011 *
#336
0$
#337
1$
b00110101 '
b11011111 (
b10101000 )
b11100100 *
#338
0$
#339
1$
b00111000 '
b11100001 (
b10101001 )
b11100101 *
#340
0$
#341
1$
b00111011 '
b11100011 (
b10101010 )
b11100110 *
#342
0$
#343
1$
b00111101 '
b11100101 (
b10101011 )
b11100111 *
#344
b00111101 #
0$
b11101000 *
#345
1$
b01000000 '
b11101000 (
b10101100 )
b11101001 *
#346
0$
#347
1$
b01000011 '
b11101010 (
b10101101 )
b11101010 *
#348
0$
#349
1$
b01000101 '
b11101011 (
b10101110 )
b11101011 *
#350
0$
#351
1$
b01001000 '
b11101101 (
b10101111 )
b11101100 *
#352
0$
#353
1$
b01001011 '
b11101111 (
b10110000 )
b11101101 *
#354
0$
#355
1$
b01001110 '
b11110000 (
b10110001 )
b11101110 *
#356
0$
#357
1$
b01010001 '
b11110001 (
b10110010 )
b11101111 *
#358
0$
#359
1$
b01010100 '
b11110011 (
b10110011 )
b11110000 *
#360
0$
#361
1$
b01010111 '
b11110100 (
b10110100 )
b11110001 *
#362
0$
#363
1$
b01011010 '
b11110101 (
b10110101 )
b11110010 *
#364
0$
#365
1$
b01011101 '
b11110110 (
b10110110 )
b11110011 *
#366
0$
#367
1$
b01100000 '
b11110111 (
b10110111 )
b11110100 *
#368
0$
#369
1$
b01100011 '
b11111000 (
b10111000 )
b11110101 *
#370
0$
#371
1$
b01100110 '
b11111001 (
b10111001 )
b11110110 *
#372
0$
#373
1$
b01101001 '
b11111010 (
b10111010 )
b11110111 *
#374
0$
#375
1$
b01101100 '
b10111011 )
b11111000 *
#376
b00111110 #
0$
b11111001 *
#377
1$
b01101111 '
b11111100 (
b10111100 )
b11111010 *
#378
0$
#379
1$
b01110010 '
b10111101 )
b11111011 *
#380
0$
#381
1$
b01110101 '
b11111101 (
b10111110 )
b11111100 *
#382
0$
#383
1$
b01111000 '
b10111111 )
b11111101 *
#384
0$
#385
1$
b01111011 '
b11000000 )
b11111110 *
#386
0$
#387
1$
b01111111 '
b11000001 )
b11111111 *
#388
0$
#389
1$
b10000010 '
b11000010 )
b00000000 *
#390
0$
#391
1$
b10000101 '
b11111110 (
b11000011 )
b00000001 *
#392
b00111111 #
0$
b00000010 *
#393
1$
b10001000 '
b11111101 (
b11000100 )
b00000011 *
#394
0$
#395
1$
b10001011 '
b11000101 )
b00000100 *
#396
0$
#397
1$
b10001110 '
b11000110 )
b00000101 *
#398
0$
#399
1$
b10010001 '
b11000111 )
b00000110 *
#400
0$
#401
1$
b10010100 '
b11111100 (
b11001000 )
b00000111 *
#402
0$
#403
1$
b10010111 '
b11001001 )
b00001000 *
#404
b01000000 #
0$
b00001001 *
#405
1$
b10011010 '
b11111010 (
b11001010 )
b00001010 *
#406
0$
#407
1$
b10011101 '
b11001011 )
b00001011 *
#408
b01000001 #
0$
b00001100 *
#409
1$
b10100000 '
b11111000 (
b11001100 )
b00001101 *
#410
0$
#411
1$
b10100011 '
b11110111 (
b11001101 )
b00001110 *
#412
0$
#413
1$
b10100110 '
b11110110 (
b11001110 )
b00001111 *
#414
0$
#415
1$
b10101001 '
b11110101 (
b11001111 )
b00010000 *
#416
0$
#417
1$
b10101100 '
b11110100 (
b11010000 )
b00010001 *
#418
0$
#419
1$
b10101111 '
b11110011 (
b11010001 )
b00010010 *
#420
0$
#421
1$
b10110010 '
b11110001 (
b11010010 )
b00010011 *
#422
0$
#423
1$
b10110101 '
b11110000 (
b11010011 )
b00010100 *
#424
0$
#425
1$
b10111000 '
b11101111 (
b11010100 )
b00010101 *
#426
0$
#427
1$
b10111010 '
b11101101 (
b11010101 )
b00010110 *
#428
0$
#429
1$
b10111101 '
b11101011 (
b11010110 )
b00010111 *
#430
0$
#431
1$
b11000000 '
b11101010 (
b11010111 )
b00011000 *
#432
0$
#433
1$
b11000010 '
b11101000 (
b11011000 )
b00011001 *
#434
0$
#435
1$
b11000101 '
b11100110 (
b11011001 )
b00011010 *
#436
0$
#437
1$
b11001000 '
b11100101 (
b11011010 )
b00011011 *
#438
0$
#439
1$
b11001010 '
b11100011 (
b11011011 )
b00011100 *
#440
0$
#441
1$
b11001101 '
b11100001 (
b11011100 )
b00011101 *
#442
0$
#443
1$
b11001111 '
b11011111 (
b11011101 )
b00011110 *
#444
b01000000 #
0$
b00011101 *
#445
1$
b11010001 '
b11011110 )
b00011110 *
#446
0$
#447
1$
b11010100 '
b11011101 (
b11011111 )
b00011111 *
#448
0$
#449
1$
b11010110 '
b11011010 (
b11100000 )
b00100000 *
#450
0$
#451
1$
b11011000 '
b11011000 (
b11100001 )
b00100001 *
#452
0$
#453
1$
b11011010 '
b11010110 (
b11100010 )
b00100010 *
#454
0$
#455
1$
b11011101 '
b11010100 (
b11100011 )
b00100011 *
#456
0$
#457
1$
b11011111 '
b11010001 (
b11100100 )
b00100100 *
#458
0$
#459
1$
b11100001 '
b11001111 (
b11100101 )
b00100101 *
#460
0$
#461
1$
b11100011 '
b11001101 (
b11100110 )
b00100110 *
#462
0$
#463
1$
b11100101 '
b11001010 (
b11100111 )
b00100111 *
#464
0$
#465
1$
b11100110 '
b11001000 (
b11101000 )
b00101000 *
#466
0$
#467
1$
b11101000 '
b11000101 (
b11101001 )
b00101001 *
#468
0$
#469
1$
b11101010 '
b11000010 (
b11101010 )
b00101010 *
#470
0$
#471
1$
b11101011 '
b11000000 (
b11101011 )
b00101011 *
#472
0$
#473
1$
b11101101 '
b10111101 (
b11101100 )
b00101100 *
#474
0$
#475
1$
b11101111 '
b10111010 (
b11101101 )
b00101101 *
#476
0$
#477
1$
b11110000 '
b10111000 (
b11101110 )
b00101110 *
#478
0$
#479
1$
b11110001 '
b10110101 (
b11101111 )
b00101111 *
#480
0$
#481
1$
b11110011 '
b10110010 (
b11110000 )
b00110000 *
#482
0$
#483
1$
b11110100 '
b10101111 (
b11110001 )
b00110001 *
#484
0$
#485
1$
b11110101 '
b10101100 (
b11110010 )
b00110010 *
#486
0$
#487
1$
b11110110 '
b10101001 (
b11110011 )
b00110011 *
#488
0$
#489
1$
b11110111 '
b10100110 (
b11110100 )
b00110100 *
#490
0$
#491
1$
b11111000 '
b10100011 (
b11110101 )
b00110101 *
#492
0$
#493
1$
b11111001 '
b10100000 (
b11110110 )
b00110110 *
#494
0$
#495
1$
b11111010 '
b10011101 (
b11110111 )
b00110111 *
#496
0$
#497
1$
b10011010 (
b11111000 )
b00111000 *
#498
0$
#499
1$
b11111011 '
b10010111 (
b11111001 )
b00111001 *
#500
0$
#501
1$
b11111100 '
b10010100 (
b11111010 )
b00111010 *
#502
0$
#503
1$
b10010001 (
b11111011 )
b00111011 *
#504
0$
#505
1$
b11111101 '
b10001110 (
b11111100 )
b00111100 *
#506
0$
#507
1$
b10001011 (
b11111101 )
b00111101 *
#508
0$
#509
1$
b10001000 (
b11111110 )
b00111110 *
#510
0$
#511
1$
b10000101 (
b11111111 )
b00111111 *
#512
0$
#513
1$
b10000010 (
b00000000 )
b01000000 *
#514
0$
#515
1$
b11111110 '
b01111110 (
b00000001 )
b01000001 *
#516
0$
#517
1$
b11111101 '
b01111011 (
b00000010 )
b01000010 *
#518
0$
#519
1$
b01111000 (
b00000011 )
b01000011 *
#520
0$
#521
1$
b01110101 (
b00000100 )
b01000100 *
#522
0$
#523
1$
b01110010 (
b00000101 )
b01000101 *
#524
0$
#525
1$
b01101111 (
b00000110 )
b01000110 *
#526
0$
#527
1$
b11111100 '
b01101100 (
b00000111 )
b01000111 *
#528
0$
#529
1$
b01101001 (
b00001000 )
b01001000 *
#530
0$
#531
1$
b11111011 '
b01100110 (
b00001001 )
b01001001 *
#532
0$
#533
1$
b11111010 '
b01100011 (
b00001010 )
b01001010 *
#534
0$
#535
1$
b01100000 (
b00001011 )
b01001011 *
#536
0$
#537
1$
b11111001 '
b01011101 (
b00001100 )
b01001100 *
#538
0$
#539
1$
b11111000 '
b01011010 (
b00001101 )
b01001101 *
#540
0$
#541
1$
b11110111 '
b01010111 (
b00001110 )
b01001110 *
#542
0$
#543
1$
b11110110 '
b01010100 (
b00001111 )
b01001111 *
#544
0$
#545
1$
b11110101 '
b01010001 (
b00010000 )
b01010000 *
#546
0$
#547
1$
b11110100 '
b01001110 (
b00010001 )
b01010001 *
#548
0$
#549
1$
b11110011 '
b01001011 (
b00010010 )
b01010010 *
#550
0$
#551
1$
b11110001 '
b01001000 (
b00010011 )
b01010011 *
#552
0$
#553
1$
b11110000 '
b01000101 (
b00010100 )
b01010100 *
#554
0$
#555
1$
b11101111 '
b01000011 (
b00010101 )
b01010101 *
#556
0$
#557
1$
b11101101 '
b01000000 (
b00010110 )
b01010110 *
#558
0$
#559
1$
b11101011 '
b00111101 (
b00010111 )
b01010111 *
#560
0$
#561
1$
b11101010 '
b00111011 (
b00011000 )
b01011000 *
#562
0$
#563
1$
b11101000 '
b00111000 (
b00011001 )
b01011001 *
#564
0$
#565
1$
b11100110 '
b00110101 (
b00011010 )
b01011010 *
#566
0$
#567
1$
b11100101 '
b00110011 (
b00011011 )
b01011011 *
#568
0$
#569
1$
b11100011 '
b00110000 (
b00011100 )
b01011100 *
#570
0$
#571
1$
b11100001 '
b00101110 (
b00011101 )
b01011101 *
#572
0$
#573
1$
b11011111 '
b00101100 (
b00011110 )
b01011110 *
#574
0$
#575
1$
b11011101 '
b00101001 (
b00011111 )
b01011111 *
#576
0$
#577
1$
b11011010 '
b00100111 (
b00100000 )
b01100000 *
#578
0$
#579
1$
b11011000 '
b00100101 (
b00100001 )
b01100001 *
#580
0$
#581
1$
b11010110 '
b00100011 (
b00100010 )
b01100010 *
#582
0$
#583
1$
b11010100 '
b00100000 (
b00100011 )
b01100011 *
#584
0$
#585
1$
b11010001 '
b00011110 (
b00100100 )
b01100100 *
#586
0$
#587
1$
b11001111 '
b00011100 (
b00100101 )
b01100101 *
#588
0$
#589
1$
b11001101 '
b00011010 (
b00100110 )
b01100110 *
#590
0$
#591
1$
b11001010 '
b00011000 (
b00100111 )
b01100111 *
#592
0$
#593
1$
b11001000 '
b00010111 (
b00101000 )
b01101000 *
#594
0$
#595
1$
b11000101 '
b00010101 (
b00101001 )
b01101001 *
#596
0$
#597
1$
b11000010 '
b00010011 (
b00101010 )
b01101010 *
#598
0$
#599
1$
b11000000 '
b00010010 (
b00101011 )
b01101011 *
#600
0$
#601
1$
b10111101 '
b00010000 (
b00101100 )
b01101100 *
#602
0$
#603
1$
b10111010 '
b00001110 (
b00101101 )
b01101101 *
#604
0$
#605
1$
b10111000 '
b00001101 (
b00101110 )
b01101110 *
#606
0$
#607
1$
b10110101 '
b00001100 (
b00101111 )
b01101111 *
#608
0$
#609
1$
b10110010 '
b00001010 (
b00110000 )
b01110000 *
#610
0$
#611
1$
b10101111 '
b00001001 (
b00110001 )
b01110001 *
#612
0$
#613
1$
b10101100 '
b00001000 (
b00110010 )
b01110010 *
#614
0$
#615
1$
b10101001 '
b00000111 (
b00110011 )
b01110011 *
#616
0$
#617
1$
b10100110 '
b00000110 (
b00110100 )
b01110100 *
#618
0$
#619
1$
b10100011 '
b00000101 (
b00110101 )
b01110101 *
#620
0$
#621
1$
b10100000 '
b00000100 (
b00110110 )
b01110110 *
#622
0$
#623
1$
b10011101 '
b00000011 (
b00110111 )
b01110111 *
#624
0$
#625
1$
b10011010 '
b00111000 )
b01111000 *
#626
0$
#627
1$
b10010111 '
b00000010 (
b00111001 )
b01111001 *
#628
0$
#629
1$
b10010100 '
b00000001 (
b00111010 )
b01111010 *
#630
0$
#631
1$
b10010001 '
b00111011 )
b01111011 *
#632
0$
#633
1$
b10001110 '
b00000000 (
b00111100 )
b01111100 *
#634
0$
#635
1$
b10001011 '
b00111101 )
b01111101 *
#636
0$
#637
1$
b10001000 '
b00111110 )
b01111110 *
#638
0$
#639
1$
b10000101 '
b00111111 )
b01111111 *
#640
0$
#641
1$
b10000010 '
b01000000 )
b10000000 *
#642
0$
#643
1$
b01111110 '
b01000001 )
b10000001 *
#644
0$
#645
1$
b01111011 '
b01000010 )
b10000010 *
#646
0$
#647
1$
b01111000 '
b01000011 )
b10000011 *
#648
0$
#649
1$
b01110101 '
b01000100 )
b10000100 *
#650
0$
#651
1$
b01110010 '
b01000101 )
b10000101 *
#652
0$
#653
1$
b01101111 '
b01000110 )
b10000110 *
#654
0$
#655
1$
b01101100 '
b00000001 (
b01000111 )
b10000111 *
#656
0$
#657
1$
b01101001 '
b01001000 )
b10001000 *
#658
0$
#659
1$
b01100110 '
b00000010 (
b01001001 )
b10001001 *
#660
0$
#661
1$
b01100011 '
b00000011 (
b01001010 )
b10001010 *
#662
0$
#663
1$
b01100000 '
b01001011 )
b10001011 *
#664
0$
#665
1$
b01011101 '
b00000100 (
b01001100 )
b10001100 *
#666
0$
#667
1$
b01011010 '
b00000101 (
b01001101 )
b10001101 *
#668
0$
#669
1$
b01010111 '
b00000110 (
b01001110 )
b10001110 *
#670
0$
#671
1$
b01010100 '
b00000111 (
b01001111 )
b10001111 *
#672
0$
#673
1$
b01010001 '
b00001000 (
b01010000 )
b10010000 *
#674
0$
#675
1$
b01001110 '
b00001001 (
b01010001 )
b10010001 *
#676
0$
#677
1$
b01001011 '
b00001010 (
b01010010 )
b10010010 *
#678
0$
